pydoc_markdown/__init__.py
pydoc_markdown/contrib/__init__.py
pydoc_markdown/contrib/loaders/__init__.py
pydoc_markdown/contrib/loaders/python.py
pydoc_markdown/contrib/processors/__init__.py
pydoc_markdown/contrib/processors/crossref.py
pydoc_markdown/contrib/processors/filter.py
pydoc_markdown/contrib/processors/google.py
pydoc_markdown/contrib/processors/pydocmd.py
pydoc_markdown/contrib/processors/smart.py
pydoc_markdown/contrib/processors/sphinx.py
pydoc_markdown/contrib/renderers/__init__.py
pydoc_markdown/contrib/renderers/docusaurus.py
pydoc_markdown/contrib/renderers/hugo.py
pydoc_markdown/contrib/renderers/jinja2.py
pydoc_markdown/contrib/renderers/markdown.py
pydoc_markdown/contrib/renderers/mkdocs.py
pydoc_markdown/contrib/source_linkers/__init__.py
pydoc_markdown/contrib/source_linkers/git.py
pydoc_markdown/interfaces.py
pydoc_markdown/main.py
pydoc_markdown/novella/preprocessor.py
pydoc_markdown/py.typed
pydoc_markdown/static.py
pydoc_markdown/util/__init__.py
pydoc_markdown/util/docspec.py
pydoc_markdown/util/knownfiles.py
pydoc_markdown/util/misc.py
pydoc_markdown/util/misc_test.py
pydoc_markdown/util/pages.py
pydoc_markdown/util/pages_test.py
pydoc_markdown/util/watchdog.py
pydoc_markdown/util/ytemplate.py
pydoc_markdown-4.8.1.dist-info/LICENSE
pydoc_markdown-4.8.1.dist-info/METADATA
pydoc_markdown-4.8.1.dist-info/WHEEL
pydoc_markdown-4.8.1.dist-info/entry_points.txt
pydoc_markdown-4.8.1.dist-info/RECORD
