Metadata-Version: 2.1
Name: pydoc-markdown
Version: 4.8.1
Summary: Create Python API documentation in Markdown format.
License: MIT
Keywords: documentation,docs,generator,markdown,pydoc
Author: Niklas Rosenstein
Author-email: rosensteinniklas@gmail.com
Requires-Python: >=3.7,<4.0
Classifier: Development Status :: 3 - Alpha
Classifier: Intended Audience :: Developers
Classifier: Intended Audience :: End Users/Desktop
Classifier: License :: OSI Approved :: MIT License
Classifier: Programming Language :: Python :: 3
Classifier: Programming Language :: Python :: 3.7
Classifier: Programming Language :: Python :: 3.8
Classifier: Programming Language :: Python :: 3.9
Classifier: Programming Language :: Python :: 3.10
Classifier: Programming Language :: Python :: 3.11
Classifier: Topic :: Software Development :: Code Generators
Classifier: Topic :: Utilities
Requires-Dist: PyYAML (>=5.0,<7.0)
Requires-Dist: click (>=7.1,<9.0)
Requires-Dist: databind.core (>=4.4.0,<5.0.0)
Requires-Dist: databind.json (>=4.4.0,<5.0.0)
Requires-Dist: docspec (>=2.2.1,<3.0.0)
Requires-Dist: docspec-python (>=2.2.1,<3.0.0)
Requires-Dist: docstring-parser (>=0.11,<0.12)
Requires-Dist: jinja2 (>=3.0.0,<4.0.0)
Requires-Dist: nr.util (>=0.7.5,<1.0.0)
Requires-Dist: requests (>=2.23.0,<3.0.0)
Requires-Dist: tomli (>=2.0.0,<3.0.0)
Requires-Dist: tomli_w (>=1.0.0,<2.0.0)
Requires-Dist: watchdog
Requires-Dist: yapf (>=0.30.0)
Project-URL: Homepage, https://github.com/NiklasRosenstein/pydoc-markdown
